eaas
eaas-list
eaassh
setup.py
eaas_tools.egg-info/PKG-INFO
eaas_tools.egg-info/SOURCES.txt
eaas_tools.egg-info/dependency_links.txt
eaas_tools.egg-info/requires.txt
eaas_tools.egg-info/top_level.txt
eaaslib/__init__.py
eaaslib/common.py
eaaslib/search.py